{
    "background-color": "#000000",
    "badge-color": "#000000",
    "bold-color": "#000000",
    "comment": "Generated with gogh-to-tilix.",
    "cursor-background-color": "#000000",
    "cursor-foreground-color": "ffa560",
    "foreground-color": "#eeeeee",
    "highlight-background-color": "#eeeeee",
    "highlight-foreground-color": "#000000",
    "name": "Ir Black",
    "palette": [
        "#4e4e4e",
        "#ff6c60",
        "#a8ff60",
        "#ffffb6",
        "#69cbfe",
        "#ff73Fd",
        "#c6c5fe",
        "#eeeeee",
        "#7c7c7c",
        "#ffb6b0",
        "#ceffac",
        "#ffffcb",
        "#b5dcfe",
        "#ff9cfe",
        "#dfdffe",
        "#ffffff"
    ],
    "use-badge-color": true,
    "use-bold-color": false,
    "use-cursor-color": false,
    "use-highlight-color": false,
    "use-theme-colors": false
}
